{
    "last_updated": "2026-02-02T16:32:10Z",
    "tokens": [
        {
            "symbol": "SANTOS",
            "price": "2.08600000",
            "priceChangePercent": "5.300",
            "volume": "588793.30000000",
            "quoteVolume": "1191521.30157000"
        },
        {
            "symbol": "LAZIO",
            "price": "0.97900000",
            "priceChangePercent": "5.496",
            "volume": "632067.39000000",
            "quoteVolume": "605655.53746000"
        },
        {
            "symbol": "PORTO",
            "price": "1.10600000",
            "priceChangePercent": "2.597",
            "volume": "1229057.55000000",
            "quoteVolume": "1344411.40542000"
        },
        {
            "symbol": "PSG",
            "price": "0.73000000",
            "priceChangePercent": "0.968",
            "volume": "686417.13000000",
            "quoteVolume": "491942.08949000"
        },
        {
            "symbol": "BAR",
            "price": "0.50600000",
            "priceChangePercent": "1.200",
            "volume": "1789031.19000000",
            "quoteVolume": "876358.17410000"
        },
        {
            "symbol": "CITY",
            "price": "0.57300000",
            "priceChangePercent": "-0.521",
            "volume": "1282136.08000000",
            "quoteVolume": "722154.08631000"
        },
        {
            "symbol": "ALPINE",
            "price": "0.45600000",
            "priceChangePercent": "2.935",
            "volume": "1583385.01000000",
            "quoteVolume": "697136.22575000"
        },
        {
            "symbol": "JUV",
            "price": "0.62300000",
            "priceChangePercent": "1.466",
            "volume": "687510.02000000",
            "quoteVolume": "417710.61261000"
        },
        {
            "symbol": "ACM",
            "price": "0.46000000",
            "priceChangePercent": "3.139",
            "volume": "1550065.90000000",
            "quoteVolume": "693122.62620000"
        },
        {
            "symbol": "ATM",
            "price": "0.87600000",
            "priceChangePercent": "2.456",
            "volume": "502055.34000000",
            "quoteVolume": "430996.12585000"
        },
        {
            "symbol": "ASR",
            "price": "1.46500000",
            "priceChangePercent": "2.448",
            "volume": "609104.80000000",
            "quoteVolume": "871100.74110000"
        },
        {
            "symbol": "OG",
            "price": "3.34500000",
            "priceChangePercent": "11.985",
            "volume": "939795.40000000",
            "quoteVolume": "2905211.57270000"
        }
    ]
}